setup.py
distributions_alongoria/Binomialdistribution.py
distributions_alongoria/Gaussiandistribution.py
distributions_alongoria/Generaldistribution.py
distributions_alongoria/__init__.py
distributions_alongoria.egg-info/PKG-INFO
distributions_alongoria.egg-info/SOURCES.txt
distributions_alongoria.egg-info/dependency_links.txt
distributions_alongoria.egg-info/not-zip-safe
distributions_alongoria.egg-info/top_level.txt